README.md
setup.py
model_connect/__init__.py
model_connect/connect.py
model_connect/constants.py
model_connect/registry.py
model_connect.egg-info/PKG-INFO
model_connect.egg-info/SOURCES.txt
model_connect.egg-info/dependency_links.txt
model_connect.egg-info/top_level.txt
model_connect/globals/__init__.py
model_connect/globals/connect.py
model_connect/globals/registry.py
model_connect/globals/options/__init__.py
model_connect/globals/options/connect.py
model_connect/globals/options/fastapi.py
model_connect/globals/options/psycopg2.py
model_connect/integrations/__init__.py
model_connect/integrations/base.py
model_connect/integrations/connect.py
model_connect/integrations/type_registry.py
model_connect/integrations/types.py
model_connect/integrations/fastapi/__init__.py
model_connect/integrations/fastapi/router.py
model_connect/integrations/fastapi/options/__init__.py
model_connect/integrations/fastapi/options/model.py
model_connect/integrations/fastapi/options/model_field.py
model_connect/integrations/json/__init__.py
model_connect/integrations/json/decoder.py
model_connect/integrations/json/encoder.py
model_connect/integrations/json/options/__init__.py
model_connect/integrations/psycopg2/__init__.py
model_connect/integrations/psycopg2/delete.py
model_connect/integrations/psycopg2/insert.py
model_connect/integrations/psycopg2/select.py
model_connect/integrations/psycopg2/update.py
model_connect/integrations/psycopg2/common/__init__.py
model_connect/integrations/psycopg2/common/processing.py
model_connect/integrations/psycopg2/common/streaming.py
model_connect/integrations/psycopg2/options/__init__.py
model_connect/integrations/psycopg2/options/model.py
model_connect/integrations/psycopg2/options/model_field.py
model_connect/options/__init__.py
model_connect/options/connect.py
model_connect/options/global/__init__.py
model_connect/options/model/__init__.py
model_connect/options/model/model.py
model_connect/options/model/query_params.py
model_connect/options/model_field/__init__.py
model_connect/options/model_field/model_field.py
model_connect/options/model_field/dtos/__init__.py
