Metadata-Version: 2.1
Name: model-connect
Version: 0.0.6
